jsonPagination/__init__.py
jsonPagination/exceptions.py
jsonPagination/paginator.py
jsonPagination-0.3.5.dist-info/LICENSE
jsonPagination-0.3.5.dist-info/METADATA
jsonPagination-0.3.5.dist-info/WHEEL
jsonPagination-0.3.5.dist-info/top_level.txt
jsonPagination-0.3.5.dist-info/RECORD
