Metadata-Version: 2.1
Name: jsonPagination
Version: 0.3.5
Summary: A versatile JSON data downloader with pagination and multithreading support.
Home-page: https://github.com/pl0psec/jsonPagination
Author: pl0psec
Author-email: contact@pl0psec.com
Keywords: json,pagination,downloader,multithreading,api
Classifier: Programming Language :: Python :: 3
Classifier: Programming Language :: Python :: 3.8
Classifier: Programming Language :: Python :: 3.9
Classifier: Programming Language :: Python :: 3.10
Classifier: Programming Language :: Python :: 3.11
Classifier: License :: OSI Approved :: MIT License
Classifier: Operating System :: OS Independent
Classifier: Intended Audience :: Developers
Classifier: Topic :: Software Development :: Libraries :: Python Modules
Requires-Python: >=3.6
License-File: LICENSE
Requires-Dist: requests>=2.28.0
Requires-Dist: tqdm>=4.65.0
